basicCalc752
