Metadata-Version: 1.1
Name: basicCalc752
Version: 0.0.0.10
Summary: A Very Stupid Calculator
Home-page: UNKNOWN
Author: Gary Ewing
Author-email: workburner4321@gmail.com
License: MIT
Keywords: calculator
Platform: UNKNOWN
Classifier: Development Status :: 5 - Production/Stable
Classifier: Intended Audience :: Education
Classifier: Operating System :: Microsoft :: Windows :: Windows 10
Classifier: License :: OSI Approved :: MIT License
Classifier: Programming Language :: Python :: 3
